tosql/__init__.py
tosql-0.2.1.dist-info/licenses/LICENSE
tosql-0.2.1.dist-info/METADATA
tosql-0.2.1.dist-info/WHEEL
tosql-0.2.1.dist-info/entry_points.txt
tosql-0.2.1.dist-info/top_level.txt
tosql-0.2.1.dist-info/RECORD
