Metadata-Version: 2.4
Name: tosql
Version: 0.2.1
Summary: tosql - pipe data to sql queries
Home-page: https://github.com/velicanu/tosql
Author: Dragos Velicanu
Author-email: d@velicanu.com
License: MIT
Classifier: License :: OSI Approved :: MIT License
Classifier: Programming Language :: Python :: 3
License-File: LICENSE
Requires-Dist: click
Requires-Dist: pandas
Dynamic: author
Dynamic: author-email
Dynamic: classifier
Dynamic: description
Dynamic: description-content-type
Dynamic: home-page
Dynamic: license
Dynamic: license-file
Dynamic: requires-dist
Dynamic: summary
